drf_hooks/__init__.py
drf_hooks/admin.py
drf_hooks/client.py
drf_hooks/migrations/0001_initial.py
drf_hooks/migrations/0002_alter_hook_user.py
drf_hooks/migrations/__init__.py
drf_hooks/models.py
drf_hooks/serializers.py
drf_hooks/signals.py
drf_hooks/urls.py
drf_hooks/utils.py
drf_hooks/views.py
drf_hooks-0.1.4.dist-info/AUTHORS.md
drf_hooks-0.1.4.dist-info/LICENSE.md
drf_hooks-0.1.4.dist-info/METADATA
drf_hooks-0.1.4.dist-info/WHEEL
drf_hooks-0.1.4.dist-info/RECORD
