Metadata-Version: 2.1
Name: drf-hooks
Version: 0.1.4
Summary: A Django app for webhooks functionality
Home-page: https://github.com/am-flow/drf-hooks
License: ISC
Keywords: django,hooks,webhooks
Author: Angira Tripathi
Author-email: angira.tripathi@am-flow.com
Requires-Python: >=3.9,<4.0
Classifier: Development Status :: 4 - Beta
Classifier: Environment :: Web Environment
Classifier: Framework :: Django
Classifier: Framework :: Django :: 4.0
Classifier: Framework :: Django :: 4.1
Classifier: Framework :: Django :: 4.2
Classifier: Intended Audience :: Developers
Classifier: License :: OSI Approved
Classifier: License :: OSI Approved :: BSD License
Classifier: Operating System :: OS Independent
Classifier: Programming Language :: Python
Classifier: Programming Language :: Python :: 3
Classifier: Programming Language :: Python :: 3.9
Classifier: Programming Language :: Python :: 3.10
Classifier: Programming Language :: Python :: 3.11
Classifier: Programming Language :: Python :: 3.12
Classifier: Programming Language :: Python :: 3.8
Classifier: Topic :: Internet :: WWW/HTTP
Classifier: Topic :: Internet :: WWW/HTTP :: Dynamic Content
Requires-Dist: Django (>=3.1,<5)
Requires-Dist: django-contrib-comments (==2.2.0)
Requires-Dist: djangorestframework (>=3.11.1)
Requires-Dist: pytz (==2025.2)
Requires-Dist: requests (>=2.32,<3.0)
Project-URL: Repository, https://github.com/am-flow/drf-hooks
